stackscope/__init__.py
stackscope/_code_dispatch.py
stackscope/_customization.py
stackscope/_extract.py
stackscope/_glue.py
stackscope/_lowlevel.py
stackscope/_lowlevel_cpython_310.py
stackscope/_lowlevel_cpython_311.py
stackscope/_lowlevel_pypy.py
stackscope/_pypy_gc_stubs.pyi
stackscope/_types.py
stackscope/_util.py
stackscope/_version.py
stackscope/lowlevel.py
stackscope/py.typed
stackscope/_tests/__init__.py
stackscope/_tests/conftest.py
stackscope/_tests/test_frames.py
stackscope/_tests/test_registry.py
stackscope/_tests/test_traceback.py
stackscope-0.2.2.dist-info/LICENSE.APACHE2
stackscope-0.2.2.dist-info/LICENSE.MIT
stackscope-0.2.2.dist-info/METADATA
stackscope-0.2.2.dist-info/WHEEL
stackscope-0.2.2.dist-info/top_level.txt
stackscope-0.2.2.dist-info/RECORD
