Metadata-Version: 2.1
Name: stackscope
Version: 0.2.2
Summary: Unusually detailed Python stack introspection
Home-page: https://github.com/oremanj/stackscope
Author: Joshua Oreman
Author-email: oremanj@gmail.com
License: MIT -or- Apache License 2.0
Keywords: async,debugging,trio,asyncio
Classifier: License :: OSI Approved :: MIT License
Classifier: License :: OSI Approved :: Apache Software License
Classifier: Operating System :: POSIX :: Linux
Classifier: Operating System :: MacOS :: MacOS X
Classifier: Operating System :: Microsoft :: Windows
Classifier: Programming Language :: Python :: 3 :: Only
Classifier: Programming Language :: Python :: Implementation :: CPython
Classifier: Programming Language :: Python :: Implementation :: PyPy
Classifier: Development Status :: 3 - Alpha
Classifier: Intended Audience :: Developers
Requires-Python: >=3.8
License-File: LICENSE.APACHE2
License-File: LICENSE.MIT
Requires-Dist: exceptiongroup >=1.0.0 ; python_version < "3.11"
